{
    "case0018": {
        "case0018_002.png": [
            0.36,
            0.12,
            0.69,
            0.45
        ],
        "case0018_003.png": [
            0.34,
            0.13,
            0.89,
            0.39
        ],
        "case0018_001.png": [
            0.34,
            0.1,
            0.69,
            0.45
        ]
    },
    "case0275": {
        "case0275_002.png": [
            0.36,
            0.64,
            0.52,
            0.78
        ],
        "case0275_001.png": [
            0.0,
            0.0,
            1.0,
            0.99
        ]
    },
    "case0127": {
        "case0127_003.png": [
            0.38,
            0.52,
            0.69,
            0.74
        ],
        "case0127_002.png": [
            0.4,
            0.08,
            0.99,
            0.9
        ],
        "case0127_001.png": [
            0.4,
            0.0,
            0.99,
            0.2
        ]
    },
    "case0043": {
        "case0043_002.png": [
            0.34,
            0.2,
            0.64,
            0.42
        ],
        "case0043_005.png": [
            0.29,
            0.0,
            0.99,
            0.16
        ],
        "case0043_004.png": [
            0.36,
            0.12,
            0.69,
            0.36
        ],
        "case0043_003.png": [
            0.28,
            0.78,
            0.44,
            0.9
        ],
        "case0043_001.png": [
            0.39,
            0.13,
            0.64,
            0.34
        ]
    },
    "case0277": {
        "case0277_001.png": [
            0.58,
            0.02,
            0.89,
            0.22
        ],
        "case0277_003.png": [
            0.36,
            0.22,
            0.56,
            0.42
        ],
        "case0277_004.png": [
            0.3,
            0.06,
            0.58,
            0.28
        ],
        "case0277_002.png": [
            0.44,
            0.04,
            0.79,
            0.28
        ]
    },
    "case0070": {
        "case0070_004.png": [
            0.36,
            0.13,
            0.99,
            0.39
        ],
        "case0070_003.png": [
            0.34,
            0.72,
            0.64,
            0.9
        ],
        "case0070_002.png": [
            0.44,
            0.55,
            0.57,
            0.66
        ],
        "case0070_005.png": [
            0.38,
            0.16,
            0.9,
            0.44
        ],
        "case0070_008.png": [
            0.41,
            0.62,
            0.57,
            0.74
        ],
        "case0070_006.png": [
            0.3,
            0.2,
            0.69,
            0.45
        ],
        "case0070_001.png": [
            0.39,
            0.64,
            0.6,
            0.8
        ],
        "case0070_010.png": [
            0.44,
            0.55,
            0.74,
            0.79
        ],
        "case0070_007.png": [
            0.3,
            0.2,
            0.69,
            0.45
        ],
        "case0070_009.png": [
            0.36,
            0.12,
            0.69,
            0.38
        ],
        "case0070_011.png": [
            0.39,
            0.74,
            0.5,
            0.91
        ]
    },
    "case0080": {
        "case0080_004.png": [
            0.39,
            0.0,
            0.99,
            0.3
        ],
        "case0080_003.png": [
            0.34,
            0.74,
            0.54,
            0.9
        ],
        "case0080_002.png": [
            0.36,
            0.38,
            0.62,
            0.52
        ],
        "case0080_005.png": [
            0.36,
            0.06,
            0.99,
            0.38
        ],
        "case0080_006.png": [
            0.49,
            0.49,
            0.64,
            0.64
        ],
        "case0080_001.png": [
            0.28,
            0.06,
            0.84,
            0.38
        ]
    },
    "case0088": {
        "case0088_003.png": [
            0.39,
            0.0,
            0.99,
            0.2
        ],
        "case0088_004.png": [
            0.28,
            0.0,
            0.99,
            0.16
        ],
        "case0088_002.png": [
            0.28,
            0.06,
            0.88,
            0.35
        ],
        "case0088_001.png": [
            0.1,
            0.1,
            0.3,
            0.3
        ]
    },
    "case0012": {
        "case0012_006.png": [
            0.39,
            0.69,
            0.59,
            0.89
        ],
        "case0012_001.png": [
            0.2,
            0.0,
            0.99,
            0.99
        ],
        "case0012_004.png": [
            0.28,
            0.06,
            0.88,
            0.34
        ],
        "case0012_003.png": [
            0.49,
            0.12,
            0.89,
            0.39
        ],
        "case0012_002.png": [
            0.48,
            0.3,
            0.69,
            0.45
        ],
        "case0012_005.png": [
            0.5,
            0.3,
            0.78,
            0.62
        ]
    },
    "case0135": {
        "case0135_006.png": [
            0.38,
            0.44,
            0.57,
            0.6
        ],
        "case0135_001.png": [
            0.39,
            0.1,
            0.69,
            0.32
        ],
        "case0135_004.png": [
            0.39,
            0.52,
            0.56,
            0.64
        ],
        "case0135_003.png": [
            0.0,
            0.0,
            1.0,
            0.99
        ],
        "case0135_002.png": [
            0.44,
            0.44,
            0.54,
            0.52
        ],
        "case0135_005.png": [
            0.0,
            0.0,
            1.0,
            0.99
        ]
    },
    "case0115": {
        "case0115_003.png": [
            0.28,
            0.74,
            0.49,
            0.9
        ],
        "case0115_004.png": [
            0.34,
            0.72,
            0.54,
            0.89
        ],
        "case0115_005.png": [
            0.3,
            0.2,
            0.5,
            0.38
        ],
        "case0115_002.png": [
            0.36,
            0.39,
            0.46,
            0.48
        ],
        "case0115_001.png": [
            0.3,
            0.26,
            0.5,
            0.46
        ],
        "case0115_006.png": [
            0.39,
            0.78,
            0.54,
            0.9
        ],
        "case0115_007.png": [
            0.29,
            0.38,
            0.44,
            0.53
        ]
    },
    "case0150": {
        "case0150_001.png": [
            0.36,
            0.12,
            0.87,
            0.4
        ],
        "case0150_003.png": [
            0.44,
            0.2,
            0.69,
            0.45
        ],
        "case0150_004.png": [
            0.34,
            0.13,
            0.84,
            0.4
        ],
        "case0150_002.png": [
            0.39,
            0.1,
            0.88,
            0.36
        ]
    },
    "case0005": {
        "case0005_002.png": [
            0.3,
            0.1,
            0.99,
            0.29
        ],
        "case0005_003.png": [
            0.28,
            0.0,
            0.99,
            0.1
        ],
        "case0005_001.png": [
            0.3,
            0.1,
            0.89,
            0.36
        ]
    },
    "case0054": {
        "case0054_001.png": [
            0.36,
            0.18,
            0.78,
            0.49
        ]
    },
    "case0212": {
        "case0212_001.png": [
            0.28,
            0.08,
            0.9,
            0.34
        ],
        "case0212_004.png": [
            0.28,
            0.74,
            0.49,
            0.89
        ],
        "case0212_003.png": [
            0.34,
            0.74,
            0.64,
            0.94
        ],
        "case0212_002.png": [
            0.28,
            0.74,
            0.49,
            0.9
        ]
    },
    "case0034": {
        "case0034_001.png": [
            0.39,
            0.69,
            0.64,
            0.89
        ],
        "case0034_005.png": [
            0.34,
            0.08,
            0.9,
            0.38
        ],
        "case0034_002.png": [
            0.44,
            0.58,
            0.66,
            0.84
        ],
        "case0034_003.png": [
            0.4,
            0.69,
            0.69,
            0.89
        ],
        "case0034_004.png": [
            0.3,
            0.12,
            0.99,
            0.34
        ]
    },
    "case0113": {
        "case0113_001.png": [
            0.3,
            0.28,
            0.4,
            0.39
        ],
        "case0113_002.png": [
            0.28,
            0.3,
            0.38,
            0.4
        ],
        "case0113_003.png": [
            0.48,
            0.58,
            0.64,
            0.72
        ]
    },
    "case0061": {
        "case0061_002.png": [
            0.39,
            0.06,
            0.69,
            0.34
        ],
        "case0061_001.png": [
            0.4,
            0.2,
            0.69,
            0.45
        ]
    },
    "case0255": {
        "case0255_001.png": [
            0.4,
            0.44,
            0.54,
            0.55
        ],
        "case0255_002.png": [
            0.4,
            0.2,
            0.89,
            0.48
        ],
        "case0255_003.png": [
            0.58,
            0.1,
            0.99,
            0.3
        ]
    },
    "case0274": {
        "case0274_002.png": [
            0.36,
            0.24,
            0.64,
            0.44
        ],
        "case0274_001.png": [
            0.39,
            0.0,
            0.99,
            0.2
        ]
    },
    "case0106": {
        "case0106_001.png": [
            0.49,
            0.46,
            0.66,
            0.62
        ],
        "case0106_002.png": [
            0.48,
            0.5,
            0.64,
            0.64
        ],
        "case0106_004.png": [
            0.48,
            0.54,
            0.62,
            0.66
        ],
        "case0106_003.png": [
            0.39,
            0.56,
            0.64,
            0.78
        ]
    },
    "case0208": {
        "case0208_001.png": [
            0.48,
            0.3,
            0.84,
            0.49
        ]
    },
    "case0200": {
        "case0200_001.png": [
            0.3,
            0.1,
            0.64,
            0.36
        ]
    },
    "case0246": {
        "case0246_001.png": [
            0.3,
            0.06,
            0.99,
            0.4
        ]
    },
    "case0247": {
        "case0247_001.png": [
            0.34,
            0.74,
            0.54,
            0.89
        ]
    }
}